ENWrapper/ENWrapper.py
ENWrapper/__init__.py
EpanetWrapper-0.1.dist-info/METADATA
EpanetWrapper-0.1.dist-info/RECORD
EpanetWrapper-0.1.dist-info/WHEEL
EpanetWrapper-0.1.dist-info/top_level.txt
